LICENSE.txt
README.md
setup.cfg
setup.py
encralize/__init__.py
encralize/encralize.py
encralize.egg-info/PKG-INFO
encralize.egg-info/SOURCES.txt
encralize.egg-info/dependency_links.txt
encralize.egg-info/requires.txt
encralize.egg-info/top_level.txt